lumis/__init__.py
lumis-0.0.1.dist-info/METADATA
lumis-0.0.1.dist-info/WHEEL
lumis-0.0.1.dist-info/top_level.txt
lumis-0.0.1.dist-info/RECORD
