Metadata-Version: 2.4
Name: lumis
Version: 0.0.1
Summary: Dummy lock package for lumis
Author: AutoPublisher
